berger_levrette/__init__.py
levrette-0.0.1.dist-info/METADATA
levrette-0.0.1.dist-info/WHEEL
levrette-0.0.1.dist-info/RECORD
