Metadata-Version: 2.1
Name: levrette
Version: 0.0.1
Summary: Berger-Levrault portals client (library and cli)
Author-Email: "Axel H." <noirbizarre@gmail.com>
License: MIT
Requires-Python: >=3.12
Requires-Dist: niquests>=3.7.2
Requires-Dist: chompjs>=1.3.0
Requires-Dist: lxml>=5.3.0
